musicxml_to_png/__init__.py
musicxml_to_png/__main__.py
musicxml_to_png/cli.py
musicxml_to_png/converter.py
musicxml_to_png/ensemble_detection.py
musicxml_to_png/extract.py
musicxml_to_png/instruments.py
musicxml_to_png/models.py
musicxml_to_png/visualize.py
musicxml_to_png-0.6.3.dist-info/licenses/LICENSE
musicxml_to_png-0.6.3.dist-info/METADATA
musicxml_to_png-0.6.3.dist-info/WHEEL
musicxml_to_png-0.6.3.dist-info/entry_points.txt
musicxml_to_png-0.6.3.dist-info/top_level.txt
musicxml_to_png-0.6.3.dist-info/RECORD
