Metadata-Version: 2.4
Name: musicxml-to-png
Version: 0.6.3
Summary: Convert MusicXML files into clean, analyzable PNG visualizations
Author: Rob Mosher
License: MIT
Project-URL: Repository, https://github.com/rob-mosher/musicxml-to-png
Project-URL: Issues, https://github.com/rob-mosher/musicxml-to-png/issues
Keywords: musicxml,music,visualization,png,notation,orchestration,music-analysis,ai
Classifier: Development Status :: 4 - Beta
Classifier: Intended Audience :: Developers
Classifier: Intended Audience :: Education
Classifier: License :: OSI Approved :: MIT License
Classifier: Programming Language :: Python :: 3
Classifier: Programming Language :: Python :: 3.12
Classifier: Topic :: Multimedia :: Graphics
Classifier: Topic :: Multimedia :: Sound/Audio
Classifier: Topic :: Software Development :: Libraries :: Python Modules
Requires-Python: >=3.12
License-File: LICENSE
Requires-Dist: music21>=9.1.0
Requires-Dist: matplotlib>=3.8.0
Requires-Dist: numpy>=1.24.0
Dynamic: license-file
